mnemosynecore/__init__.py
mnemosynecore/config.py
mnemosynecore/mattermost.py
mnemosynecore/secrets.py
mnemosynecore/superset.py
mnemosynecore/warnings.py
mnemosynecore/data_bases/__init__.py
mnemosynecore/data_bases/vertica.py
mnemosynecore/vault/__init__.py
mnemosynecore/vault/client.py
mnemosynecore/vault/univ_conn.py
mnemosynecore-1.0.2.dist-info/METADATA
mnemosynecore-1.0.2.dist-info/WHEEL
mnemosynecore-1.0.2.dist-info/top_level.txt
mnemosynecore-1.0.2.dist-info/RECORD
